rest_collection_client/__init__.py
rest_collection_client/exc.py
rest_collection_client/http/__init__.py
rest_collection_client/http/abc.py
rest_collection_client/http/container.py
rest_collection_client/http/exc.py
rest_collection_client/http/mixin.py
rest_collection_client/http/request.py
rest_collection_client/join/__init__.py
rest_collection_client/join/columns.py
rest_collection_client/join/rule.py
rest_collection_client/join/sequence.py
rest_collection_client/py.typed
rest_collection_client/response/__init__.py
rest_collection_client/response/deserialize.py
rest_collection_client/response/rename.py
rest_collection_client/response/response.py
rest_collection_client/typing.py
rest_collection_client-0.7.0.dist-info/LICENSE.txt
rest_collection_client-0.7.0.dist-info/WHEEL
rest_collection_client-0.7.0.dist-info/METADATA
rest_collection_client-0.7.0.dist-info/RECORD
