Metadata-Version: 2.1
Name: rest-collection-client
Version: 0.7.0
Summary: Rest collection library HTTP client.
Home-page: https://bitbucket.org/p-app/rest_collection_client
License: MIT
Author: Vladimir V. Pivovarov
Author-email: admin@p-app.ru
Maintainer: Vladimir V. Pivovarov
Maintainer-email: admin@p-app.ru
Requires-Python: >=3.8,<4.0
Classifier: Development Status :: 5 - Production/Stable
Classifier: Framework :: aiohttp
Classifier: Intended Audience :: Developers
Classifier: License :: OSI Approved :: MIT License
Classifier: Programming Language :: Python :: 3
Classifier: Programming Language :: Python :: 3.10
Classifier: Programming Language :: Python :: 3.8
Classifier: Programming Language :: Python :: 3.9
Classifier: Topic :: Internet :: WWW/HTTP
Classifier: Topic :: Software Development :: Libraries :: Python Modules
Provides-Extra: ujson
Requires-Dist: aiohttp (>=3.8.0,<4.0.0)
Requires-Dist: collections-extension (>=0.5.0,<0.6.0)
Requires-Dist: pandas (>=1.2.0,<2.0.0)
Requires-Dist: ujson; extra == "ujson"
Project-URL: Repository, https://bitbucket.org/p-app/rest_collection_client
